odoo/addons/account_move_analytic_recreate/README.rst
odoo/addons/account_move_analytic_recreate/__init__.py
odoo/addons/account_move_analytic_recreate/__manifest__.py
odoo/addons/account_move_analytic_recreate/i18n/account_move_analytic_recreate.pot
odoo/addons/account_move_analytic_recreate/models/__init__.py
odoo/addons/account_move_analytic_recreate/models/account_move.py
odoo/addons/account_move_analytic_recreate/static/description/icon.png
odoo11_addon_account_move_analytic_recreate-11.0.1.0.0.99.dev1.dist-info/METADATA
odoo11_addon_account_move_analytic_recreate-11.0.1.0.0.99.dev1.dist-info/WHEEL
odoo11_addon_account_move_analytic_recreate-11.0.1.0.0.99.dev1.dist-info/top_level.txt
odoo11_addon_account_move_analytic_recreate-11.0.1.0.0.99.dev1.dist-info/RECORD
